cognite/neat_cfihos_handler/__init__.py
cognite/neat_cfihos_handler/_processor.py
cognite/neat_cfihos_handler/_reader.py
cognite/neat_cfihos_handler/plugin.py
cognite/neat_cfihos_handler/framework/__init__.py
cognite/neat_cfihos_handler/framework/common/__init__.py
cognite/neat_cfihos_handler/framework/common/constants.py
cognite/neat_cfihos_handler/framework/common/generic_classes.py
cognite/neat_cfihos_handler/framework/common/log.py
cognite/neat_cfihos_handler/framework/common/reader.py
cognite/neat_cfihos_handler/framework/common/utils.py
cognite/neat_cfihos_handler/framework/importer/__init__.py
cognite/neat_cfihos_handler/framework/importer/_cfihos2data_model.py
cognite/neat_cfihos_handler/framework/importer/base_model_interpreter.py
cognite/neat_cfihos_handler/framework/importer/cfihos_loader.py
cognite/neat_cfihos_handler/framework/importer/data_sheets_column_mappings.py
cognite/neat_cfihos_handler/framework/neat_data_model/__init__.py
cognite/neat_cfihos_handler/framework/neat_data_model/model_creater.py
cognite/neat_cfihos_handler/framework/processing/__init__.py
cognite/neat_cfihos_handler/framework/processing/model_managers/__init__.py
cognite/neat_cfihos_handler/framework/processing/model_managers/base_cfihos_manager.py
cognite/neat_cfihos_handler/framework/processing/model_managers/model_manager_provider.py
cognite/neat_cfihos_handler/framework/processing/model_managers/sparse_model_manager.py
cognite/neat_cfihos_handler/framework/processing/processors/__init__.py
cognite/neat_cfihos_handler/framework/processing/processors/base_processor.py
cognite/neat_cfihos_handler/framework/processing/processors/sparse_properties.py
cognite_neat_cfihos_handler-0.2.dist-info/licenses/LICENSE
cognite_neat_cfihos_handler-0.2.dist-info/METADATA
cognite_neat_cfihos_handler-0.2.dist-info/WHEEL
cognite_neat_cfihos_handler-0.2.dist-info/entry_points.txt
cognite_neat_cfihos_handler-0.2.dist-info/top_level.txt
cognite_neat_cfihos_handler-0.2.dist-info/RECORD
