Metadata-Version: 2.4
Name: cognite-neat-cfihos-handler
Version: 0.2
Summary: CFIHOS standard processor for NEAT
Author-email: Ali Majed <ali.majed@cognite.com>
License-Expression: Apache-2.0
Requires-Python: >=3.10
License-File: LICENSE
Requires-Dist: chardet>=5.2.0
Requires-Dist: cognite-neat==0.123.33
Requires-Dist: pbr>=7.0.1
Requires-Dist: pre-commit>=4.3.0
Requires-Dist: pytest>=8.4.2
Requires-Dist: pytest-mock>=3.15.1
Dynamic: license-file
